pixmatch/__init__.py
pixmatch/__main__.py
pixmatch/utils.py
pixmatch/gui/__init__.py
pixmatch/gui/pixmatch.ico
pixmatch/gui/utils.py
pixmatch/gui/widgets.py
pixmatch/gui/zip.png
pixmatch-0.1.3.dist-info/licenses/LICENSE
pixmatch-0.1.3.dist-info/METADATA
pixmatch-0.1.3.dist-info/WHEEL
pixmatch-0.1.3.dist-info/top_level.txt
pixmatch-0.1.3.dist-info/RECORD
