Metadata-Version: 2.4
Name: pixmatch
Version: 0.1.3
Summary: A modern VisiPics replacement.
Author-email: Ryan Heard <ryanwheard@gmail.com>
Project-URL: Repository, https://github.com/rheard/pixmatch
Classifier: Programming Language :: Python :: 3
Classifier: Programming Language :: Python :: 3.9
Classifier: Programming Language :: Python :: 3.10
Classifier: Programming Language :: Python :: 3.11
Classifier: Programming Language :: Python :: 3.12
Classifier: Programming Language :: Python :: 3.13
Classifier: Programming Language :: Python :: Implementation :: CPython
Requires-Python: >=3.9
License-File: LICENSE
Requires-Dist: Pillow
Requires-Dist: imagehash
Requires-Dist: Send2Trash
Provides-Extra: gui
Requires-Dist: PySide6; extra == "gui"
Dynamic: license-file
